file_analysis_mcp/__init__.py
file_analysis_mcp/server.py
file_analysis_mcp-0.1.0.dist-info/METADATA
file_analysis_mcp-0.1.0.dist-info/WHEEL
file_analysis_mcp-0.1.0.dist-info/entry_points.txt
file_analysis_mcp-0.1.0.dist-info/licenses/LICENSE
file_analysis_mcp-0.1.0.dist-info/RECORD
