Metadata-Version: 2.4
Name: file_analysis_mcp
Version: 0.1.0
Summary: MCP server for text file analysis
Project-URL: github, https://github.com/varunidealabs/file_analysis_mcp.git
Author-email: VARUN SAI <varunsai.srinivas@gmail.com>
License-Expression: MIT
License-File: LICENSE
Classifier: Development Status :: 3 - Alpha
Classifier: Intended Audience :: Developers
Classifier: Operating System :: OS Independent
Classifier: Programming Language :: Python :: 3
Classifier: Topic :: Text Processing :: Linguistic
Requires-Python: >=3.10
Requires-Dist: fastmcp>=0.1.0
